nobinobi_core/__init__.py
nobinobi_core/admin.py
nobinobi_core/apps.py
nobinobi_core/forms.py
nobinobi_core/functions.py
nobinobi_core/models.py
nobinobi_core/urls.py
nobinobi_core/views.py
nobinobi_core/widgets.py
nobinobi_core/locale/en/LC_MESSAGES/django.mo
nobinobi_core/locale/fr/LC_MESSAGES/django.mo
nobinobi_core/migrations/0001_initial.py
nobinobi_core/migrations/0002_organisation_organisationclosure.py
nobinobi_core/migrations/0003_alter_holiday_date.py
nobinobi_core/migrations/__init__.py
nobinobi_core/static/css/bootstrap-datetimepicker-standalone.css
nobinobi_core/static/css/bootstrap-datetimepicker.css
nobinobi_core/static/css/bootstrap-datetimepicker.min.css
nobinobi_core/static/css/nobinobi_core.css
nobinobi_core/static/js/bootstrap-datetimepicker.min.js
nobinobi_core/static/js/moment-with-locales.min.js
nobinobi_core/static/js/nobinobi_core.js
nobinobi_core/templates/includes/messages.html
nobinobi_core/templates/layout/checkboxselectmultiple_act.html
nobinobi_core/templates/layout/checkboxselectmultiple_image.html
nobinobi_core/templates/layout/checkboxselectmultiple_inline.html
nobinobi_core/templates/layout/checkboxselectmultiple_inline_act.html
nobinobi_core/templates/layout/checkboxselectmultiple_inline_image.html
nobinobi_core/templates/layout/field_errors_block.html
nobinobi_core/templates/layout/help_text.html
nobinobi_core/templates/layout/radioselect.html
nobinobi_core/templates/layout/radioselect_image.html
nobinobi_core/templates/layout/radioselect_inline.html
nobinobi_core/templates/layout/radioselect_inline_image.html
nobinobi_core/templates/layout/sj/collation_general.html
nobinobi_core/templates/nobinobi_core/add_official_holiday.html
nobinobi_core/templates/nobinobi_core/base.html
nobinobi_core/templatetags/__init__.py
nobinobi_core/templatetags/get_dict_value.py
nobinobi_core/templatetags/get_user_method.py
nobinobi_core/templatetags/math.py
nobinobi_core/templatetags/notifications_tags_custom.py
nobinobi_core-0.1.4.9.dist-info/AUTHORS.rst
nobinobi_core-0.1.4.9.dist-info/LICENSE
nobinobi_core-0.1.4.9.dist-info/METADATA
nobinobi_core-0.1.4.9.dist-info/WHEEL
nobinobi_core-0.1.4.9.dist-info/top_level.txt
nobinobi_core-0.1.4.9.dist-info/RECORD
