Metadata-Version: 2.1
Name: nobinobi-core
Version: 0.1.4.9
Summary: Core for application Nobinobi
Home-page: https://github.com/prolibre-ch/nobinobi-core
Author: Florian Alu
Author-email: alu@prolibre.com
Keywords: nobinobi-core
Classifier: Development Status :: 5 - Production/Stable
Classifier: Framework :: Django :: 3.1
Classifier: Intended Audience :: Developers
Classifier: License :: OSI Approved :: GNU Affero General Public License v3 or later (AGPLv3+)
Classifier: Natural Language :: English
Classifier: Programming Language :: Python :: 3.6
Classifier: Programming Language :: Python :: 3.7
Classifier: Programming Language :: Python :: 3.8
License-File: LICENSE
License-File: AUTHORS.rst
Requires-Dist: django (>=3.2.19)
Requires-Dist: django-model-utils (>=4.1.1)
Requires-Dist: arrow (>=1.1.1)
Requires-Dist: django-crispy-forms (>=2.0)
Requires-Dist: crispy-bootstrap5 (>=0.7)
